Nour/__init__.py
Nour/nour.py
Nour/util.py
Nour-1.0.1.dist-info/METADATA
Nour-1.0.1.dist-info/WHEEL
Nour-1.0.1.dist-info/top_level.txt
Nour-1.0.1.dist-info/RECORD
