Metadata-Version: 2.1
Name: Nour
Version: 1.0.1
Summary: Nour is a tool which converts Arabic words, letters or sentences to and from  Braille notations.
Home-page: https://github.com/khalidt/Nour
Author: Khalid Alkhaldi
Author-email: K.T.Alkhaldi@gmail.com
License: UNKNOWN
Keywords: Conversion,Braille,development,Arabic to Braille
Platform: UNKNOWN
Classifier: Programming Language :: Python :: 3
Classifier: Programming Language :: Python :: 3.6
Classifier: Programming Language :: Python :: 3.7
Classifier: Programming Language :: Python :: 3.8
Classifier: License :: OSI Approved :: GNU General Public License v3 (GPLv3)
Classifier: Operating System :: OS Independent
Classifier: Environment :: Console
Classifier: Natural Language :: English
Classifier: Development Status :: 3 - Alpha
Requires-Python: >=3.6
